meterpreter_traffic_parser/__init__.py
meterpreter_traffic_parser/packet.py
meterpreter_traffic_parser/packet_header.py
meterpreter_traffic_parser/tlv_unit.py
meterpreter_traffic_parser/enums/__init__.py
meterpreter_traffic_parser/enums/packet_meta_type.py
meterpreter_traffic_parser/enums/packet_tlv_type.py
meterpreter_traffic_parser/enums/tlv_type.py
meterpreter_traffic_parser/exceptions/__init__.py
meterpreter_traffic_parser/helpers/__init__.py
meterpreter_traffic_parser-0.0.2.dist-info/LICENSE
meterpreter_traffic_parser-0.0.2.dist-info/METADATA
meterpreter_traffic_parser-0.0.2.dist-info/WHEEL
meterpreter_traffic_parser-0.0.2.dist-info/top_level.txt
meterpreter_traffic_parser-0.0.2.dist-info/RECORD
