Metadata-Version: 2.1
Name: meterpreter-traffic-parser
Version: 0.0.2
Summary: Meterpreter traffic parser
Home-page: https://github.com/SpartaEN/meterpreter-traffic-parser
Author: SpartaEN
Author-email: nya@sparta-en.org
License: UNKNOWN
Project-URL: Bug Tracker, https://github.com/SpartaEN/meterpreter-traffic-parser/issues
Platform: UNKNOWN
Classifier: Programming Language :: Python :: 3
Classifier: License :: OSI Approved :: MIT License
Classifier: Operating System :: OS Independent
Requires-Python: >=3.6
